litdb/__init__.py
litdb/app.py
litdb/audio.py
litdb/bibtex.py
litdb/chat.py
litdb/cli.py
litdb/coa.py
litdb/crawl.py
litdb/db.py
litdb/doe_collaborators.py
litdb/extract.py
litdb/gpt.py
litdb/images.py
litdb/lab.py
litdb/lsearch.py
litdb/mcp.py
litdb/openalex.py
litdb/pdf.py
litdb/research.py
litdb/server.py
litdb/utils.py
litdb/youtube.py
litdb-2.1.8.dist-info/METADATA
litdb-2.1.8.dist-info/WHEEL
litdb-2.1.8.dist-info/entry_points.txt
litdb-2.1.8.dist-info/top_level.txt
litdb-2.1.8.dist-info/RECORD
