Metadata-Version: 2.4
Name: litdb
Version: 2.1.8
Summary: A literature database tool with GPT integration.
Author-email: John Kitchin <jkitchin@andrew.cmu.edu>
Maintainer-email: John Kitchin <jkitchin@andrew.cmu.edu>
License-Expression: MIT
Project-URL: Homepage, https://github.com/jkitchin/litdb
Requires-Dist: toml
Requires-Dist: tomlkit
Requires-Dist: requests
Requires-Dist: pymupdf4llm
Requires-Dist: docling
Requires-Dist: langchain
Requires-Dist: tqdm
Requires-Dist: libsql-experimental
Requires-Dist: sentence-transformers
Requires-Dist: transformers
Requires-Dist: click
Requires-Dist: rich
Requires-Dist: beautifulsoup4
Requires-Dist: ratelimit
Requires-Dist: python-docx
Requires-Dist: python-pptx
Requires-Dist: nbconvert
Requires-Dist: nbformat
Requires-Dist: ollama
Requires-Dist: litellm
Requires-Dist: dateparser
Requires-Dist: jinja2
Requires-Dist: pytesseract
Requires-Dist: pillow
Requires-Dist: bibtexparser
Requires-Dist: pandas
Requires-Dist: more-itertools
Requires-Dist: nameparser
Requires-Dist: tabulate
Requires-Dist: IPython
Requires-Dist: yt_dlp
Requires-Dist: webvtt-py
Requires-Dist: streamlit
Requires-Dist: pyperclip
Requires-Dist: pillow
Requires-Dist: pillow_heif
Requires-Dist: scrapy
Requires-Dist: backoff
Requires-Dist: gpt_researcher
Requires-Dist: duckduckgo-search
Requires-Dist: langchain_ollama
Requires-Dist: langchain_google_genai
Requires-Dist: langchain_anthropic
Requires-Dist: mistune
Requires-Dist: htmldocx
Requires-Dist: docx
Requires-Dist: md2pdf
Requires-Dist: pypandoc
Requires-Dist: mcp[cli]
